{
  "$schema": "http://json-schema.org/draft-07/schema#",
  "definitions": {
    "SyncMetadata_pennylane_customers": {
      "type": "object",
      "additionalProperties": false
    },
    "PennylaneCustomer": {
      "type": "object",
      "properties": {
        "id": {
          "type": "string"
        },
        "first_name": {
          "type": "string"
        },
        "last_name": {
          "type": "string"
        },
        "gender": {
          "type": "string"
        },
        "address": {
          "type": "string"
        },
        "vat_number": {
          "type": [
            "string",
            "null"
          ]
        },
        "postal_code": {
          "type": [
            "string",
            "null"
          ]
        },
        "city": {
          "type": [
            "string",
            "null"
          ]
        },
        "country_alpha2": {
          "type": [
            "string",
            "null"
          ]
        },
        "recipient": {
          "type": [
            "string",
            "null"
          ]
        },
        "source_id": {
          "type": [
            "string",
            "null"
          ]
        },
        "emails": {
          "anyOf": [
            {
              "type": "array",
              "items": {
                "type": "string"
              }
            },
            {
              "type": "null"
            }
          ]
        },
        "billing_iban": {
          "type": [
            "string",
            "null"
          ]
        },
        "delivery_address": {
          "anyOf": [
            {
              "type": "object",
              "properties": {
                "address": {
                  "type": "string"
                },
                "postal_code": {
                  "type": [
                    "string",
                    "null"
                  ]
                },
                "city": {
                  "type": [
                    "string",
                    "null"
                  ]
                },
                "country_alpha2": {
                  "type": [
                    "string",
                    "null"
                  ]
                }
              },
              "required": [
                "address",
                "postal_code",
                "city",
                "country_alpha2"
              ],
              "additionalProperties": false
            },
            {
              "type": "null"
            }
          ]
        },
        "delivery_postal_code": {
          "type": [
            "string",
            "null"
          ]
        },
        "delivery_country_alpha2": {
          "type": [
            "string",
            "null"
          ]
        },
        "payment_conditions": {
          "type": [
            "string",
            "null"
          ]
        },
        "phone": {
          "type": [
            "string",
            "null"
          ]
        },
        "reference": {
          "type": [
            "string",
            "null"
          ]
        },
        "notes": {
          "type": [
            "string",
            "null"
          ]
        }
      },
      "required": [
        "id",
        "first_name",
        "last_name",
        "gender",
        "address",
        "vat_number",
        "postal_code",
        "city",
        "country_alpha2",
        "recipient",
        "source_id",
        "emails",
        "billing_iban",
        "delivery_address",
        "delivery_postal_code",
        "delivery_country_alpha2",
        "payment_conditions",
        "phone",
        "reference",
        "notes"
      ],
      "additionalProperties": false
    },
    "SyncMetadata_pennylane_suppliers": {
      "type": "object",
      "additionalProperties": false
    },
    "PennylaneSupplier": {
      "type": "object",
      "properties": {
        "name": {
          "type": "string"
        },
        "id": {
          "type": "string"
        },
        "reg_no": {
          "type": "string"
        },
        "address": {
          "type": "string"
        },
        "postal_code": {
          "type": "string"
        },
        "city": {
          "type": "string"
        },
        "country_alpha2": {
          "type": "string"
        },
        "recipient": {
          "type": "string"
        },
        "vat_number": {
          "type": "string"
        },
        "source_id": {
          "type": "string"
        },
        "emails": {
          "type": "array",
          "items": {
            "type": "string"
          }
        },
        "iban": {
          "type": "string"
        },
        "payment_conditions": {
          "type": "string"
        },
        "phone": {
          "type": "string"
        },
        "reference": {
          "type": "string"
        },
        "notes": {
          "type": "string"
        }
      },
      "required": [
        "name",
        "id",
        "reg_no",
        "address",
        "postal_code",
        "city",
        "country_alpha2",
        "recipient",
        "vat_number",
        "source_id",
        "emails",
        "iban",
        "payment_conditions",
        "phone",
        "reference",
        "notes"
      ],
      "additionalProperties": false
    },
    "SyncMetadata_pennylane_invoices": {
      "type": "object",
      "additionalProperties": false
    },
    "PennylaneInvoice": {
      "type": "object",
      "properties": {
        "id": {
          "type": "string"
        },
        "amount": {
          "type": [
            "string",
            "null"
          ]
        },
        "billing_subscription": {
          "anyOf": [
            {
              "type": "object",
              "properties": {
                "id": {
                  "type": [
                    "string",
                    "null"
                  ]
                }
              },
              "required": [
                "id"
              ],
              "additionalProperties": false
            },
            {
              "type": "null"
            }
          ]
        },
        "categories": {
          "anyOf": [
            {
              "type": "array",
              "items": {
                "anyOf": [
                  {
                    "type": "string"
                  },
                  {
                    "type": "null"
                  },
                  {
                    "type": "string",
                    "format": "date-time"
                  }
                ]
              }
            },
            {
              "type": "null"
            }
          ]
        },
        "currency": {
          "type": [
            "string",
            "null"
          ]
        },
        "currency_amount": {
          "type": [
            "string",
            "null"
          ]
        },
        "currency_amount_before_tax": {
          "type": [
            "string",
            "null"
          ]
        },
        "currency_tax": {
          "type": [
            "string",
            "null"
          ]
        },
        "customer": {
          "type": "object",
          "properties": {
            "customer_type": {
              "type": "string"
            },
            "first_name": {
              "type": "string"
            },
            "last_name": {
              "type": "string"
            },
            "country_alpha2": {
              "type": "string"
            },
            "gender": {
              "type": [
                "string",
                "null"
              ]
            },
            "address": {
              "type": "string"
            },
            "postal_code": {
              "type": "string"
            },
            "city": {
              "type": "string"
            },
            "source_id": {
              "type": "string"
            },
            "emails": {
              "type": "array",
              "items": {
                "type": "string"
              }
            },
            "billing_iban": {
              "type": "string"
            },
            "delivery_address": {
              "anyOf": [
                {
                  "type": "string"
                },
                {
                  "type": "object",
                  "properties": {
                    "address": {
                      "type": "string"
                    },
                    "postal_code": {
                      "type": [
                        "string",
                        "null"
                      ]
                    },
                    "city": {
                      "type": [
                        "string",
                        "null"
                      ]
                    },
                    "country_alpha2": {
                      "type": [
                        "string",
                        "null"
                      ]
                    }
                  },
                  "required": [
                    "address",
                    "postal_code",
                    "city",
                    "country_alpha2"
                  ],
                  "additionalProperties": false
                }
              ]
            },
            "vat_number": {
              "type": [
                "string",
                "null"
              ]
            },
            "delivery_postal_code": {
              "type": "string"
            },
            "delivery_city": {
              "type": "string"
            },
            "delivery_country_alpha2": {
              "type": "string"
            },
            "payment_conditions": {
              "type": "string"
            },
            "phone": {
              "type": "string"
            },
            "reference": {
              "type": "string"
            },
            "notes": {
              "type": "string"
            },
            "mandate": {
              "type": "object",
              "properties": {
                "provider": {
                  "type": "string"
                },
                "source_id": {
                  "type": "string"
                }
              },
              "required": [
                "provider",
                "source_id"
              ],
              "additionalProperties": false
            },
            "plan_item": {
              "type": "object",
              "properties": {
                "number": {
                  "type": "string"
                },
                "label": {
                  "type": "string"
                },
                "enabled": {
                  "type": "boolean"
                },
                "vat_rate": {
                  "type": "string"
                },
                "country_alpha2": {
                  "type": "string"
                },
                "description": {
                  "type": "string"
                }
              },
              "required": [
                "number",
                "label",
                "enabled",
                "vat_rate",
                "country_alpha2",
                "description"
              ],
              "additionalProperties": false
            }
          },
          "required": [
            "customer_type",
            "first_name",
            "last_name",
            "country_alpha2",
            "gender",
            "address",
            "postal_code",
            "city",
            "source_id",
            "emails",
            "billing_iban",
            "delivery_address",
            "vat_number",
            "delivery_postal_code",
            "delivery_city",
            "delivery_country_alpha2",
            "payment_conditions",
            "phone",
            "reference",
            "notes",
            "mandate",
            "plan_item"
          ],
          "additionalProperties": false
        },
        "customer_name": {
          "type": "string"
        },
        "customer_validation_needed": {
          "type": [
            "boolean",
            "null"
          ]
        },
        "date": {
          "anyOf": [
            {
              "type": "string",
              "format": "date-time"
            },
            {
              "type": "string"
            }
          ]
        },
        "deadline": {
          "type": [
            "string",
            "null"
          ]
        },
        "discount": {
          "type": [
            "string",
            "null"
          ]
        },
        "discount_type": {
          "type": [
            "string",
            "null"
          ]
        },
        "exchange_rate": {
          "type": [
            "number",
            "null"
          ]
        },
        "file_url": {
          "type": [
            "string",
            "null"
          ]
        },
        "filename": {
          "type": [
            "string",
            "null"
          ]
        },
        "fully_paid_at": {
          "anyOf": [
            {
              "type": "string",
              "format": "date-time"
            },
            {
              "type": "null"
            }
          ]
        },
        "imputation_dates": {
          "anyOf": [
            {
              "type": "object",
              "properties": {
                "start_date": {
                  "type": "string"
                },
                "end_date": {
                  "type": "string"
                }
              },
              "required": [
                "start_date",
                "end_date"
              ],
              "additionalProperties": false
            },
            {
              "type": "null"
            }
          ]
        },
        "invoice_number": {
          "type": [
            "string",
            "null"
          ]
        },
        "is_draft": {
          "type": "boolean"
        },
        "is_estimate": {
          "type": "boolean"
        },
        "label": {
          "type": [
            "string",
            "null"
          ]
        },
        "language": {
          "type": [
            "string",
            "null"
          ]
        },
        "line_items": {
          "type": "array",
          "items": {
            "type": [
              "number",
              "string",
              "null"
            ]
          }
        },
        "line_items_sections_attributes": {
          "type": "array",
          "items": {
            "type": [
              "string",
              "null",
              "number"
            ]
          }
        },
        "matched_transactions": {
          "type": "array",
          "items": {
            "anyOf": [
              {
                "type": "string"
              },
              {
                "type": "null"
              },
              {
                "type": "string",
                "format": "date-time"
              }
            ]
          }
        },
        "paid": {
          "type": "boolean"
        },
        "payments": {
          "$comment": "() =>[]"
        },
        "pdf_invoice_free_text": {
          "type": "string"
        },
        "pdf_invoice_subject": {
          "type": "string"
        },
        "public_url": {
          "type": [
            "string",
            "null"
          ]
        },
        "quote_group_uuid": {
          "type": [
            "string",
            "null"
          ]
        },
        "remaining_amount": {
          "type": [
            "string",
            "null"
          ]
        },
        "source": {
          "type": [
            "string",
            "null"
          ]
        },
        "special_mention": {
          "type": [
            "string",
            "null"
          ]
        },
        "status": {
          "type": [
            "string",
            "null"
          ]
        },
        "transactions_reference": {
          "anyOf": [
            {
              "type": "object",
              "properties": {
                "banking_provider": {
                  "type": [
                    "string",
                    "null"
                  ]
                },
                "provider_field_name": {
                  "type": [
                    "string",
                    "null"
                  ]
                },
                "provider_field_value": {
                  "type": [
                    "string",
                    "null"
                  ]
                }
              },
              "required": [
                "banking_provider",
                "provider_field_name",
                "provider_field_value"
              ],
              "additionalProperties": false
            },
            {
              "type": "null"
            }
          ]
        },
        "updated_at": {
          "anyOf": [
            {
              "type": "string",
              "format": "date-time"
            },
            {
              "type": "string"
            }
          ]
        }
      },
      "required": [
        "id",
        "amount",
        "billing_subscription",
        "categories",
        "currency",
        "currency_amount",
        "currency_amount_before_tax",
        "currency_tax",
        "customer",
        "customer_name",
        "customer_validation_needed",
        "date",
        "deadline",
        "discount",
        "discount_type",
        "exchange_rate",
        "file_url",
        "filename",
        "fully_paid_at",
        "imputation_dates",
        "invoice_number",
        "is_draft",
        "is_estimate",
        "label",
        "language",
        "line_items",
        "line_items_sections_attributes",
        "matched_transactions",
        "paid",
        "payments",
        "pdf_invoice_free_text",
        "pdf_invoice_subject",
        "public_url",
        "quote_group_uuid",
        "remaining_amount",
        "source",
        "special_mention",
        "status",
        "transactions_reference",
        "updated_at"
      ],
      "additionalProperties": false
    },
    "SyncMetadata_pennylane_products": {
      "type": "object",
      "additionalProperties": false
    },
    "PennylaneProduct": {
      "type": "object",
      "properties": {
        "id": {
          "type": "string"
        },
        "source_id": {
          "type": "string"
        },
        "label": {
          "type": "string"
        },
        "description": {
          "type": "string"
        },
        "unit": {
          "type": "string"
        },
        "price_before_tax": {
          "type": "number"
        },
        "price": {
          "type": "number"
        },
        "vat_rate": {
          "type": "string"
        },
        "currency": {
          "type": "string"
        },
        "reference": {
          "type": [
            "string",
            "null"
          ]
        },
        "substance": {
          "type": [
            "string",
            "null"
          ]
        }
      },
      "required": [
        "id",
        "source_id",
        "label",
        "description",
        "unit",
        "price_before_tax",
        "price",
        "vat_rate",
        "currency",
        "reference",
        "substance"
      ],
      "additionalProperties": false
    },
    "ActionInput_pennylane_createcustomer": {
      "type": "object",
      "properties": {
        "customer_type": {
          "type": "string"
        },
        "first_name": {
          "type": "string"
        },
        "last_name": {
          "type": "string"
        },
        "country_alpha2": {
          "type": "string"
        },
        "gender": {
          "type": [
            "string",
            "null"
          ]
        },
        "address": {
          "type": "string"
        },
        "postal_code": {
          "type": "string"
        },
        "city": {
          "type": "string"
        },
        "source_id": {
          "type": "string"
        },
        "emails": {
          "type": "array",
          "items": {
            "type": "string"
          }
        },
        "billing_iban": {
          "type": "string"
        },
        "delivery_address": {
          "anyOf": [
            {
              "type": "string"
            },
            {
              "type": "object",
              "properties": {
                "address": {
                  "type": "string"
                },
                "postal_code": {
                  "type": [
                    "string",
                    "null"
                  ]
                },
                "city": {
                  "type": [
                    "string",
                    "null"
                  ]
                },
                "country_alpha2": {
                  "type": [
                    "string",
                    "null"
                  ]
                }
              },
              "required": [
                "address",
                "postal_code",
                "city",
                "country_alpha2"
              ],
              "additionalProperties": false
            }
          ]
        },
        "vat_number": {
          "type": [
            "string",
            "null"
          ]
        },
        "delivery_postal_code": {
          "type": "string"
        },
        "delivery_city": {
          "type": "string"
        },
        "delivery_country_alpha2": {
          "type": "string"
        },
        "payment_conditions": {
          "type": "string"
        },
        "phone": {
          "type": "string"
        },
        "reference": {
          "type": "string"
        },
        "notes": {
          "type": "string"
        },
        "mandate": {
          "type": "object",
          "properties": {
            "provider": {
              "type": "string"
            },
            "source_id": {
              "type": "string"
            }
          },
          "required": [
            "provider",
            "source_id"
          ],
          "additionalProperties": false
        },
        "plan_item": {
          "type": "object",
          "properties": {
            "number": {
              "type": "string"
            },
            "label": {
              "type": "string"
            },
            "enabled": {
              "type": "boolean"
            },
            "vat_rate": {
              "type": "string"
            },
            "country_alpha2": {
              "type": "string"
            },
            "description": {
              "type": "string"
            }
          },
          "required": [
            "number",
            "label",
            "enabled",
            "vat_rate",
            "country_alpha2",
            "description"
          ],
          "additionalProperties": false
        }
      },
      "required": [
        "customer_type",
        "first_name",
        "last_name",
        "country_alpha2",
        "gender",
        "address",
        "postal_code",
        "city",
        "source_id",
        "emails",
        "billing_iban",
        "delivery_address",
        "vat_number",
        "delivery_postal_code",
        "delivery_city",
        "delivery_country_alpha2",
        "payment_conditions",
        "phone",
        "reference",
        "notes",
        "mandate",
        "plan_item"
      ],
      "additionalProperties": false
    },
    "ActionOutput_pennylane_createcustomer": {
      "type": "object",
      "properties": {
        "success": {
          "type": "boolean"
        },
        "source_id": {
          "type": "string"
        }
      },
      "required": [
        "success",
        "source_id"
      ],
      "additionalProperties": false
    },
    "ActionInput_pennylane_createinvoice": {
      "type": "object",
      "properties": {
        "create_customer": {
          "type": "boolean"
        },
        "create_products": {
          "type": "boolean"
        },
        "update_customer": {
          "type": "boolean"
        },
        "date": {
          "type": "string"
        },
        "deadline": {
          "type": "string"
        },
        "draft": {
          "type": "boolean"
        },
        "customer_source_id": {
          "type": "string"
        },
        "external_id": {
          "type": [
            "string",
            "null"
          ]
        },
        "pdf_invoice_free_text": {
          "type": [
            "string",
            "null"
          ]
        },
        "pdf_invoice_subject": {
          "type": [
            "string",
            "null"
          ]
        },
        "currency": {
          "type": "string"
        },
        "special_mention": {
          "type": [
            "string",
            "null"
          ]
        },
        "discount": {
          "type": "number"
        },
        "language": {
          "type": "string"
        },
        "transactions_reference": {
          "type": "object",
          "properties": {
            "banking_provider": {
              "type": [
                "string",
                "null"
              ]
            },
            "provider_field_name": {
              "type": [
                "string",
                "null"
              ]
            },
            "provider_field_value": {
              "type": [
                "string",
                "null"
              ]
            }
          },
          "required": [
            "banking_provider",
            "provider_field_name",
            "provider_field_value"
          ],
          "additionalProperties": false
        },
        "line_items": {
          "anyOf": [
            {
              "type": "array",
              "items": {
                "type": [
                  "string",
                  "number"
                ]
              }
            },
            {
              "type": "array",
              "items": {
                "anyOf": [
                  {
                    "type": "string"
                  },
                  {
                    "type": "number"
                  },
                  {
                    "type": "object",
                    "properties": {
                      "source_id": {
                        "type": "string"
                      },
                      "price": {
                        "type": "number"
                      },
                      "vat_rate": {
                        "type": "string"
                      },
                      "unit": {
                        "type": "string"
                      }
                    },
                    "required": [
                      "source_id",
                      "price",
                      "vat_rate",
                      "unit"
                    ],
                    "additionalProperties": false
                  }
                ]
              }
            }
          ]
        },
        "categories": {
          "type": "array",
          "items": {
            "type": [
              "string",
              "number",
              "null"
            ]
          }
        },
        "line_items_sections_attributes": {
          "type": "array",
          "items": {
            "type": [
              "string",
              "null",
              "number"
            ]
          }
        },
        "imputation_dates": {
          "type": "object",
          "properties": {
            "start_date": {
              "type": "string"
            },
            "end_date": {
              "type": "string"
            }
          },
          "required": [
            "start_date",
            "end_date"
          ],
          "additionalProperties": false
        }
      },
      "required": [
        "create_customer",
        "create_products",
        "update_customer",
        "date",
        "deadline",
        "draft",
        "customer_source_id",
        "external_id",
        "pdf_invoice_free_text",
        "pdf_invoice_subject",
        "currency",
        "special_mention",
        "discount",
        "language",
        "transactions_reference",
        "line_items",
        "categories",
        "line_items_sections_attributes",
        "imputation_dates"
      ],
      "additionalProperties": false
    },
    "ActionOutput_pennylane_createinvoice": {
      "type": "object",
      "properties": {
        "success": {
          "type": "boolean"
        },
        "source_id": {
          "type": "string"
        }
      },
      "required": [
        "success",
        "source_id"
      ],
      "additionalProperties": false
    },
    "ActionInput_pennylane_createsupplier": {
      "type": "object",
      "properties": {
        "name": {
          "type": "string"
        },
        "reg_no": {
          "type": "string"
        },
        "address": {
          "type": "string"
        },
        "postal_code": {
          "type": "string"
        },
        "city": {
          "type": "string"
        },
        "country_alpha2": {
          "type": "string"
        },
        "recipient": {
          "type": "string"
        },
        "vat_number": {
          "type": "string"
        },
        "source_id": {
          "type": "string"
        },
        "emails": {
          "type": "array",
          "items": {
            "type": "string"
          }
        },
        "iban": {
          "type": "string"
        },
        "payment_conditions": {
          "type": "string"
        },
        "phone": {
          "type": "string"
        },
        "reference": {
          "type": "string"
        },
        "notes": {
          "type": "string"
        }
      },
      "required": [
        "name",
        "reg_no",
        "address",
        "postal_code",
        "city",
        "country_alpha2",
        "recipient",
        "vat_number",
        "source_id",
        "emails",
        "iban",
        "payment_conditions",
        "phone",
        "reference",
        "notes"
      ],
      "additionalProperties": false
    },
    "ActionOutput_pennylane_createsupplier": {
      "type": "object",
      "properties": {
        "success": {
          "type": "boolean"
        },
        "source_id": {
          "type": "string"
        }
      },
      "required": [
        "success",
        "source_id"
      ],
      "additionalProperties": false
    },
    "ActionInput_pennylane_updatecustomer": {
      "type": "object",
      "properties": {
        "id": {
          "type": "string"
        },
        "first_name": {
          "type": "string"
        },
        "last_name": {
          "type": "string"
        },
        "gender": {
          "type": "string"
        },
        "address": {
          "type": "string"
        },
        "vat_number": {
          "type": [
            "string",
            "null"
          ]
        },
        "postal_code": {
          "type": [
            "string",
            "null"
          ]
        },
        "city": {
          "type": [
            "string",
            "null"
          ]
        },
        "country_alpha2": {
          "type": [
            "string",
            "null"
          ]
        },
        "recipient": {
          "type": [
            "string",
            "null"
          ]
        },
        "source_id": {
          "type": [
            "string",
            "null"
          ]
        },
        "emails": {
          "anyOf": [
            {
              "type": "array",
              "items": {
                "type": "string"
              }
            },
            {
              "type": "null"
            }
          ]
        },
        "billing_iban": {
          "type": [
            "string",
            "null"
          ]
        },
        "delivery_address": {
          "anyOf": [
            {
              "type": "object",
              "properties": {
                "address": {
                  "type": "string"
                },
                "postal_code": {
                  "type": [
                    "string",
                    "null"
                  ]
                },
                "city": {
                  "type": [
                    "string",
                    "null"
                  ]
                },
                "country_alpha2": {
                  "type": [
                    "string",
                    "null"
                  ]
                }
              },
              "required": [
                "address",
                "postal_code",
                "city",
                "country_alpha2"
              ],
              "additionalProperties": false
            },
            {
              "type": "null"
            }
          ]
        },
        "delivery_postal_code": {
          "type": [
            "string",
            "null"
          ]
        },
        "delivery_country": {
          "type": [
            "string",
            "null"
          ]
        },
        "delivery_country_alpha2": {
          "type": [
            "string",
            "null"
          ]
        },
        "payment_conditions": {
          "type": [
            "string",
            "null"
          ]
        },
        "phone": {
          "type": [
            "string",
            "null"
          ]
        },
        "reference": {
          "type": [
            "string",
            "null"
          ]
        },
        "notes": {
          "type": [
            "string",
            "null"
          ]
        }
      },
      "required": [
        "id",
        "first_name",
        "last_name",
        "gender",
        "address",
        "vat_number",
        "postal_code",
        "city",
        "country_alpha2",
        "recipient",
        "source_id",
        "emails",
        "billing_iban",
        "delivery_address",
        "delivery_postal_code",
        "delivery_country",
        "delivery_country_alpha2",
        "payment_conditions",
        "phone",
        "reference",
        "notes"
      ],
      "additionalProperties": false
    },
    "ActionOutput_pennylane_updatecustomer": {
      "type": "object",
      "properties": {
        "success": {
          "type": "boolean"
        },
        "source_id": {
          "type": "string"
        }
      },
      "required": [
        "success",
        "source_id"
      ],
      "additionalProperties": false
    },
    "ActionInput_pennylane_updateinvoice": {
      "type": "object",
      "properties": {
        "id": {
          "type": "string"
        },
        "label": {
          "type": [
            "string",
            "null"
          ]
        },
        "invoice_number": {
          "type": [
            "string",
            "null"
          ]
        },
        "quote_group_uuid": {
          "type": "string"
        },
        "is_draft": {
          "type": "boolean"
        },
        "is_estimate": {
          "type": "boolean"
        },
        "currency": {
          "type": "string"
        },
        "amount": {
          "type": "string"
        },
        "currency_amount": {
          "type": "string"
        },
        "currency_amount_before_tax": {
          "type": "string"
        },
        "exchange_rate": {
          "type": "number"
        },
        "date": {
          "type": [
            "string",
            "null"
          ]
        },
        "deadline": {
          "type": [
            "string",
            "null"
          ]
        },
        "currency_tax": {
          "type": "string"
        },
        "language": {
          "type": "string"
        },
        "paid": {
          "type": "boolean"
        },
        "fully_paid_at": {
          "type": [
            "string",
            "null"
          ]
        },
        "status": {
          "type": [
            "string",
            "null"
          ]
        },
        "discount": {
          "type": "string"
        },
        "discount_type": {
          "type": "string"
        },
        "public_url": {
          "type": "string"
        },
        "file_url": {
          "type": [
            "string",
            "null"
          ]
        },
        "filename": {
          "type": "string"
        },
        "remaining_amount": {
          "type": "string"
        },
        "source": {
          "type": "string",
          "const": "InvoiceSource"
        },
        "special_mention": {
          "type": [
            "string",
            "null"
          ]
        },
        "updated_at": {
          "type": "string"
        },
        "imputation_dates": {
          "anyOf": [
            {
              "type": "object",
              "properties": {
                "start_date": {
                  "type": "string"
                },
                "end_date": {
                  "type": "string"
                }
              },
              "required": [
                "start_date",
                "end_date"
              ],
              "additionalProperties": false
            },
            {
              "type": "null"
            }
          ]
        },
        "customer": {
          "type": "object",
          "properties": {
            "customer_type": {
              "type": "string"
            },
            "first_name": {
              "type": "string"
            },
            "last_name": {
              "type": "string"
            },
            "country_alpha2": {
              "type": "string"
            },
            "gender": {
              "type": [
                "string",
                "null"
              ]
            },
            "address": {
              "type": "string"
            },
            "postal_code": {
              "type": "string"
            },
            "city": {
              "type": "string"
            },
            "source_id": {
              "type": "string"
            },
            "emails": {
              "type": "array",
              "items": {
                "type": "string"
              }
            },
            "billing_iban": {
              "type": "string"
            },
            "delivery_address": {
              "anyOf": [
                {
                  "type": "string"
                },
                {
                  "type": "object",
                  "properties": {
                    "address": {
                      "type": "string"
                    },
                    "postal_code": {
                      "type": [
                        "string",
                        "null"
                      ]
                    },
                    "city": {
                      "type": [
                        "string",
                        "null"
                      ]
                    },
                    "country_alpha2": {
                      "type": [
                        "string",
                        "null"
                      ]
                    }
                  },
                  "required": [
                    "address",
                    "postal_code",
                    "city",
                    "country_alpha2"
                  ],
                  "additionalProperties": false
                }
              ]
            },
            "vat_number": {
              "type": [
                "string",
                "null"
              ]
            },
            "delivery_postal_code": {
              "type": "string"
            },
            "delivery_city": {
              "type": "string"
            },
            "delivery_country_alpha2": {
              "type": "string"
            },
            "payment_conditions": {
              "type": "string"
            },
            "phone": {
              "type": "string"
            },
            "reference": {
              "type": "string"
            },
            "notes": {
              "type": "string"
            },
            "mandate": {
              "type": "object",
              "properties": {
                "provider": {
                  "type": "string"
                },
                "source_id": {
                  "type": "string"
                }
              },
              "required": [
                "provider",
                "source_id"
              ],
              "additionalProperties": false
            },
            "plan_item": {
              "type": "object",
              "properties": {
                "number": {
                  "type": "string"
                },
                "label": {
                  "type": "string"
                },
                "enabled": {
                  "type": "boolean"
                },
                "vat_rate": {
                  "type": "string"
                },
                "country_alpha2": {
                  "type": "string"
                },
                "description": {
                  "type": "string"
                }
              },
              "required": [
                "number",
                "label",
                "enabled",
                "vat_rate",
                "country_alpha2",
                "description"
              ],
              "additionalProperties": false
            }
          },
          "required": [
            "customer_type",
            "first_name",
            "last_name",
            "country_alpha2",
            "gender",
            "address",
            "postal_code",
            "city",
            "source_id",
            "emails",
            "billing_iban",
            "delivery_address",
            "vat_number",
            "delivery_postal_code",
            "delivery_city",
            "delivery_country_alpha2",
            "payment_conditions",
            "phone",
            "reference",
            "notes",
            "mandate",
            "plan_item"
          ],
          "additionalProperties": false
        },
        "line_items_sections_attributes": {
          "type": "array",
          "items": {
            "type": [
              "string",
              "null",
              "number"
            ]
          }
        },
        "line_items": {
          "type": "array",
          "items": {
            "type": [
              "number",
              "string",
              "null"
            ]
          }
        },
        "categories": {
          "type": "array",
          "items": {
            "anyOf": [
              {
                "type": "string"
              },
              {
                "type": "null"
              },
              {
                "type": "string",
                "format": "date-time"
              }
            ]
          }
        },
        "transactions_reference": {
          "type": "object",
          "properties": {
            "banking_provider": {
              "type": [
                "string",
                "null"
              ]
            },
            "provider_field_name": {
              "type": [
                "string",
                "null"
              ]
            },
            "provider_field_value": {
              "type": [
                "string",
                "null"
              ]
            }
          },
          "required": [
            "banking_provider",
            "provider_field_name",
            "provider_field_value"
          ],
          "additionalProperties": false
        },
        "payments": {
          "type": "array",
          "items": {
            "anyOf": [
              {
                "type": "string"
              },
              {
                "type": "string",
                "format": "date-time"
              }
            ]
          }
        },
        "matched_transactions": {
          "type": "array",
          "items": {
            "anyOf": [
              {
                "type": "string"
              },
              {
                "type": "null"
              },
              {
                "type": "string",
                "format": "date-time"
              }
            ]
          }
        },
        "pdf_invoice_free_text": {
          "type": "string"
        },
        "pdf_invoice_subject": {
          "type": "string"
        },
        "billing_subscription": {
          "anyOf": [
            {
              "type": "object",
              "properties": {
                "id": {
                  "type": [
                    "string",
                    "null"
                  ]
                }
              },
              "required": [
                "id"
              ],
              "additionalProperties": false
            },
            {
              "type": "null"
            }
          ]
        }
      },
      "required": [
        "id",
        "label",
        "invoice_number",
        "quote_group_uuid",
        "is_draft",
        "is_estimate",
        "currency",
        "amount",
        "currency_amount",
        "currency_amount_before_tax",
        "exchange_rate",
        "date",
        "deadline",
        "currency_tax",
        "language",
        "paid",
        "fully_paid_at",
        "status",
        "discount",
        "discount_type",
        "public_url",
        "file_url",
        "filename",
        "remaining_amount",
        "source",
        "special_mention",
        "updated_at",
        "imputation_dates",
        "customer",
        "line_items_sections_attributes",
        "line_items",
        "categories",
        "transactions_reference",
        "payments",
        "matched_transactions",
        "pdf_invoice_free_text",
        "pdf_invoice_subject",
        "billing_subscription"
      ],
      "additionalProperties": false
    },
    "ActionOutput_pennylane_updateinvoice": {
      "type": "object",
      "properties": {
        "success": {
          "type": "boolean"
        },
        "source_id": {
          "type": "string"
        }
      },
      "required": [
        "success",
        "source_id"
      ],
      "additionalProperties": false
    },
    "ActionInput_pennylane_updatesupplier": {
      "type": "object",
      "properties": {
        "source_id": {
          "type": "string"
        },
        "name": {
          "type": "string"
        },
        "reg_no": {
          "type": "string"
        },
        "address": {
          "type": "string"
        },
        "postal_code": {
          "type": "string"
        },
        "city": {
          "type": "string"
        },
        "country_alpha2": {
          "type": "string"
        },
        "recipient": {
          "type": "string"
        },
        "vat_number": {
          "type": "string"
        },
        "emails": {
          "type": "array",
          "items": {
            "type": "string"
          }
        },
        "iban": {
          "type": "string"
        },
        "payment_conditions": {
          "type": "string"
        },
        "phone": {
          "type": "string"
        },
        "reference": {
          "type": "string"
        },
        "notes": {
          "type": "string"
        }
      },
      "required": [
        "source_id",
        "name",
        "reg_no",
        "address",
        "postal_code",
        "city",
        "country_alpha2",
        "recipient",
        "vat_number",
        "emails",
        "iban",
        "payment_conditions",
        "phone",
        "reference",
        "notes"
      ],
      "additionalProperties": false
    },
    "ActionOutput_pennylane_updatesupplier": {
      "type": "object",
      "properties": {
        "success": {
          "type": "boolean"
        },
        "source_id": {
          "type": "string"
        }
      },
      "required": [
        "success",
        "source_id"
      ],
      "additionalProperties": false
    },
    "ActionInput_pennylane_createproduct": {
      "type": "object",
      "properties": {
        "source_id": {
          "type": "string"
        },
        "label": {
          "type": "string"
        },
        "description": {
          "type": "string"
        },
        "unit": {
          "type": "string"
        },
        "price_before_tax": {
          "type": "number"
        },
        "price": {
          "type": "number"
        },
        "vat_rate": {
          "type": "string"
        },
        "currency": {
          "type": "string"
        },
        "reference": {
          "type": [
            "string",
            "null"
          ]
        },
        "substance": {
          "type": [
            "string",
            "null"
          ]
        }
      },
      "required": [
        "source_id",
        "label",
        "description",
        "unit",
        "price_before_tax",
        "price",
        "vat_rate",
        "currency",
        "reference",
        "substance"
      ],
      "additionalProperties": false
    },
    "ActionOutput_pennylane_createproduct": {
      "type": "object",
      "properties": {
        "success": {
          "type": "boolean"
        },
        "source_id": {
          "type": "string"
        }
      },
      "required": [
        "success",
        "source_id"
      ],
      "additionalProperties": false
    },
    "ActionInput_pennylane_updateproduct": {
      "type": "object",
      "properties": {
        "source_id": {
          "type": "string"
        },
        "label": {
          "type": "string"
        },
        "description": {
          "type": "string"
        },
        "unit": {
          "type": "string"
        },
        "price_before_tax": {
          "type": "number"
        },
        "price": {
          "type": "number"
        },
        "vat_rate": {
          "type": "string"
        },
        "currency": {
          "type": "string"
        },
        "reference": {
          "type": [
            "string",
            "null"
          ]
        },
        "substance": {
          "type": [
            "string",
            "null"
          ]
        }
      },
      "required": [
        "source_id",
        "label",
        "description",
        "unit",
        "price_before_tax",
        "price",
        "vat_rate",
        "currency",
        "reference",
        "substance"
      ],
      "additionalProperties": false
    },
    "ActionOutput_pennylane_updateproduct": {
      "type": "object",
      "properties": {
        "success": {
          "type": "boolean"
        },
        "source_id": {
          "type": "string"
        }
      },
      "required": [
        "success",
        "source_id"
      ],
      "additionalProperties": false
    }
  },
  "$comment": "This file was generated by Nango (v0.64.1)"
}