[
    {
        "created_at": "2024-06-19T19:51:27.000Z",
        "updated_at": "2024-06-19T19:51:28.000Z",
        "id": "73",
        "txn_date": "2024-06-03",
        "remaining_credit": 0,
        "balance_cents": 0,
        "total_amt_cents": 10000,
        "customer_name": "Amy's Bird Sanctuary",
        "bill_address": {
            "city": null,
            "line1": "Amy Lauterbach",
            "postal_code": null,
            "country": null,
            "id": "79"
        },
        "items": [
            {
                "id": "1",
                "description": "Pest Control Services",
                "qty": 1,
                "unit_price_cents": 10000,
                "amount_cents": 10000
            }
        ]
    }
]
