[
    {
        "id": "00602AVVMSTLEDAVfxnl",
        "firstName": "Kelvin",
        "lastName": "Wari",
        "email": "kelvin@nango.dev"
    },
    {
        "id": "00602BMPNVWGSJRVfyxj",
        "firstName": "Kelvin",
        "lastName": "Wari",
        "email": "kelvin-1@nango.dev"
    },
    {
        "id": "00602WQVTMPZYKFDfyxk",
        "firstName": "Kelvin",
        "lastName": "Wari",
        "email": "kelvin-2@nango.dev"
    },
    {
        "id": "00602OVEOFTRCFNRfyxl",
        "firstName": "Kelvin",
        "lastName": "Wari",
        "email": "kelvin-3@nango.dev"
    },
    {
        "id": "00602DTPSEXGZGPDfyxm",
        "firstName": "Kelvin",
        "lastName": "Wari",
        "email": "kelvin-4@nango.dev"
    },
    {
        "id": "00602WVHQAQICTRAfyxn",
        "firstName": "Kelvin",
        "lastName": "Wari",
        "email": "kelvin-5@nango.dev"
    },
    {
        "id": "00602VXTOYMTXEGQfyxo",
        "firstName": "Kelvin",
        "lastName": "Wari",
        "email": "kelvin-6@nango.dev"
    },
    {
        "id": "00602TWPKMXMEBPWfyxp",
        "firstName": "Kelvin",
        "lastName": "Wari",
        "email": "kelvin-7@nango.dev"
    },
    {
        "id": "00602HFGCHDMMZMKfyxq",
        "firstName": "Kelvin",
        "lastName": "Wari",
        "email": "kelvin-8@nango.dev"
    },
    {
        "id": "00602XSVNNKGFBABfyxr",
        "firstName": "Kelvin",
        "lastName": "Wari",
        "email": "kelvin-9@nango.dev"
    },
    {
        "id": "00602CXVWJJABNCJfyxs",
        "firstName": "Kelvin",
        "lastName": "Wari",
        "email": "kelvin-10@nango.dev"
    },
    {
        "id": "00602OLHCMGKVOSWfyxu",
        "firstName": "Kelvin",
        "lastName": "Wari",
        "email": "kelvin-11@nango.dev"
    },
    {
        "id": "00602EMVEHBIDMDVfyxv",
        "firstName": "Kelvin",
        "lastName": "Wari",
        "email": "kelvin-10@test.dev"
    },
    {
        "id": "00602TGBGIRTAIEQfyxx",
        "firstName": "Kelvin",
        "lastName": "Wari",
        "email": "kelvin-11@test.dev"
    },
    {
        "id": "00602TVPVXMHNJFZfyy1",
        "firstName": "Kelvin",
        "lastName": "Mock",
        "email": "kelvin-12@test.dev"
    }
]
