{
  "$schema": "http://json-schema.org/draft-07/schema#",
  "definitions": {
    "ActionInput_google_docs_fetchdocument": {
      "type": "object",
      "properties": {
        "id": {
          "type": "string"
        }
      },
      "required": [
        "id"
      ],
      "additionalProperties": false
    },
    "ActionOutput_google_docs_fetchdocument": {
      "type": "object",
      "properties": {
        "documentId": {
          "type": "string"
        },
        "title": {
          "type": "string"
        },
        "url": {
          "type": "string"
        },
        "tabs": {
          "$comment": "() =>[]"
        },
        "revisionId": {
          "type": "string"
        },
        "suggestionsViewMode": {
          "type": "string",
          "enum": [
            "DEFAULT_FOR_CURRENT_ACCESS",
            "SUGGESTIONS_INLINE",
            "PREVIEW_SUGGESTIONS_ACCEPTED",
            "PREVIEW_WITHOUT_SUGGESTIONS"
          ]
        },
        "body": {
          "type": "object",
          "additionalProperties": false
        },
        "headers": {
          "type": "object",
          "additionalProperties": false
        },
        "footers": {
          "type": "object",
          "additionalProperties": false
        },
        "footnotes": {
          "type": "object",
          "additionalProperties": false
        },
        "documentStyle": {
          "type": "object",
          "additionalProperties": false
        },
        "suggestedDocumentStyleChanges": {
          "type": "object",
          "additionalProperties": false
        },
        "namedStyles": {
          "type": "object",
          "additionalProperties": false
        },
        "suggestedNamedStylesChanges": {
          "type": "object",
          "additionalProperties": false
        },
        "lists": {
          "type": "object",
          "additionalProperties": false
        },
        "namedRanges": {
          "type": "object",
          "additionalProperties": false
        },
        "inlineObjects": {
          "type": "object",
          "additionalProperties": false
        },
        "positionedObjects": {
          "type": "object",
          "additionalProperties": false
        }
      },
      "required": [
        "documentId",
        "title",
        "url",
        "tabs",
        "revisionId",
        "suggestionsViewMode",
        "body",
        "headers",
        "footers",
        "footnotes",
        "documentStyle",
        "suggestedDocumentStyleChanges",
        "namedStyles",
        "suggestedNamedStylesChanges",
        "lists",
        "namedRanges",
        "inlineObjects",
        "positionedObjects"
      ],
      "additionalProperties": false
    }
  },
  "$comment": "This file was generated by Nango (v0.64.1)"
}